[
{
"id":"wa01",
"heroId":"ha01",
"atk":78,
"def":35,
"matk":130,
"mdef":30,
"hp":508,
"atkUp":5.36,
"defUp":2.3,
"matkUp":7.68,
"mdefUp":2,
"hpUp":49.45,
"isOpen":"true"
},
{
"id":"wa02",
"heroId":"ha02",
"atk":182,
"def":48,
"matk":105,
"mdef":38,
"hp":551,
"atkUp":10.31,
"defUp":2.84,
"matkUp":6.84,
"mdefUp":2.52,
"hpUp":57.16,
"isOpen":"true"
},
{
"id":"wa03",
"heroId":"ha03",
"atk":130,
"def":81,
"matk":111,
"mdef":55,
"hp":978,
"atkUp":6.52,
"defUp":5.18,
"matkUp":5.39,
"mdefUp":3.44,
"hpUp":72.61,
"isOpen":"true"
},
{
"id":"wa04",
"heroId":"ha04",
"atk":172,
"def":45,
"matk":90,
"mdef":36,
"hp":524,
"atkUp":9.74,
"defUp":2.66,
"matkUp":5.84,
"mdefUp":2.37,
"hpUp":54.33,
"isOpen":"true"
},
{
"id":"wa05",
"heroId":"ha05",
"atk":177,
"def":46,
"matk":110,
"mdef":37,
"hp":482,
"atkUp":10.02,
"defUp":2.7,
"matkUp":7.16,
"mdefUp":2.46,
"hpUp":49.89,
"isOpen":"true"
},
{
"id":"wa06",
"heroId":"ha06",
"atk":139,
"def":65,
"matk":143,
"mdef":81,
"hp":714,
"atkUp":6.14,
"defUp":3.7,
"matkUp":7.18,
"mdefUp":4.81,
"hpUp":78.81,
"isOpen":"true"
},
{
"id":"wa07",
"heroId":"ha07",
"atk":126,
"def":81,
"matk":108,
"mdef":55,
"hp":969,
"atkUp":6.35,
"defUp":5.22,
"matkUp":5.19,
"mdefUp":3.39,
"hpUp":71.88,
"isOpen":"true"
},
{
"id":"wa08",
"heroId":"ha08",
"atk":104,
"def":40,
"matk":193,
"mdef":43,
"hp":574,
"atkUp":5.22,
"defUp":2.58,
"matkUp":8.92,
"mdefUp":2.68,
"hpUp":56.43,
"isOpen":"true"
},
{
"id":"wa09",
"heroId":"ha09",
"atk":93,
"def":35,
"matk":195,
"mdef":39,
"hp":564,
"atkUp":4.68,
"defUp":2.34,
"matkUp":9.05,
"mdefUp":2.49,
"hpUp":55.32,
"isOpen":"true"
},
{
"id":"wa10",
"heroId":"ha10",
"atk":173,
"def":49,
"matk":102,
"mdef":37,
"hp":532,
"atkUp":9.77,
"defUp":2.86,
"matkUp":6.66,
"mdefUp":2.49,
"hpUp":55.13,
"isOpen":"true"
},
{
"id":"wa11",
"heroId":"ha11",
"atk":131,
"def":37,
"matk":76,
"mdef":32,
"hp":484,
"atkUp":7.82,
"defUp":2.49,
"matkUp":5.19,
"mdefUp":2.16,
"hpUp":47.07,
"isOpen":"true"
},
{
"id":"wa12",
"heroId":"ha12",
"atk":128,
"def":77,
"matk":116,
"mdef":59,
"hp":988,
"atkUp":6.46,
"defUp":4.96,
"matkUp":5.58,
"mdefUp":3.68,
"hpUp":73.33,
"isOpen":"true"
},
{
"id":"wa13",
"heroId":"ha13",
"atk":119,
"def":57,
"matk":126,
"mdef":72,
"hp":696,
"atkUp":5.28,
"defUp":3.17,
"matkUp":6.37,
"mdefUp":4.23,
"hpUp":76.83,
"isOpen":"true"
},
{
"id":"wa14",
"heroId":"ha14",
"atk":94,
"def":32,
"matk":190,
"mdef":36,
"hp":554,
"atkUp":4.7,
"defUp":2.14,
"matkUp":8.78,
"mdefUp":2.27,
"hpUp":54.4,
"isOpen":"true"
},
{
"id":"wa15",
"heroId":"ha15",
"atk":128,
"def":58,
"matk":121,
"mdef":74,
"hp":680,
"atkUp":6.46,
"defUp":3.29,
"matkUp":5.33,
"mdefUp":4.36,
"hpUp":74.93,
"isOpen":"true"
},
{
"id":"wa16",
"heroId":"ha16",
"atk":131,
"def":35,
"matk":75,
"mdef":30,
"hp":523,
"atkUp":7.76,
"defUp":2.28,
"matkUp":5.15,
"mdefUp":2.05,
"hpUp":50.85,
"isOpen":"true"
},
{
"id":"wa17",
"heroId":"ha17",
"atk":102,
"def":32,
"matk":191,
"mdef":40,
"hp":527,
"atkUp":5.12,
"defUp":2.12,
"matkUp":8.86,
"mdefUp":2.49,
"hpUp":51.76,
"isOpen":"true"
},
{
"id":"wa18",
"heroId":"hb01",
"atk":184,
"def":46,
"matk":106,
"mdef":37,
"hp":482,
"atkUp":10.37,
"defUp":2.76,
"matkUp":6.84,
"mdefUp":2.4,
"hpUp":50.08,
"isOpen":"true"
},
{
"id":"wa19",
"heroId":"hb02",
"atk":183,
"def":46,
"matk":107,
"mdef":39,
"hp":486,
"atkUp":10.33,
"defUp":2.81,
"matkUp":6.92,
"mdefUp":2.55,
"hpUp":50.46,
"isOpen":"true"
},
{
"id":"wa20",
"heroId":"hb03",
"atk":97,
"def":37,
"matk":201,
"mdef":42,
"hp":571,
"atkUp":4.86,
"defUp":2.46,
"matkUp":9.35,
"mdefUp":2.6,
"hpUp":56.11,
"isOpen":"true"
},
{
"id":"wa21",
"heroId":"hb04",
"atk":120,
"def":67,
"matk":131,
"mdef":74,
"hp":696,
"atkUp":5.3,
"defUp":3.77,
"matkUp":6.63,
"mdefUp":4.41,
"hpUp":76.6,
"isOpen":"true"
},
{
"id":"wa22",
"heroId":"hb05",
"atk":191,
"def":43,
"matk":89,
"mdef":35,
"hp":493,
"atkUp":10.8,
"defUp":2.52,
"matkUp":5.82,
"mdefUp":2.31,
"hpUp":51.15,
"isOpen":"true"
},
{
"id":"wa23",
"heroId":"hb06",
"atk":184,
"def":45,
"matk":89,
"mdef":35,
"hp":498,
"atkUp":10.38,
"defUp":2.69,
"matkUp":5.8,
"mdefUp":2.34,
"hpUp":51.72,
"isOpen":"true"
},
{
"id":"wa24",
"heroId":"hb07",
"atk":139,
"def":40,
"matk":77,
"mdef":34,
"hp":492,
"atkUp":8.23,
"defUp":2.63,
"matkUp":5.29,
"mdefUp":2.28,
"hpUp":47.85,
"isOpen":"true"
},
{
"id":"wa25",
"heroId":"hb08",
"atk":88,
"def":34,
"matk":193,
"mdef":38,
"hp":557,
"atkUp":4.47,
"defUp":2.26,
"matkUp":8.95,
"mdefUp":2.41,
"hpUp":54.59,
"isOpen":"true"
},
{
"id":"wa26",
"heroId":"hb09",
"atk":94,
"def":33,
"matk":177,
"mdef":37,
"hp":552,
"atkUp":4.72,
"defUp":2.19,
"matkUp":8.24,
"mdefUp":2.29,
"hpUp":54.18,
"isOpen":"true"
},
{
"id":"wa27",
"heroId":"hb10",
"atk":126,
"def":82,
"matk":110,
"mdef":61,
"hp":953,
"atkUp":6.34,
"defUp":5.19,
"matkUp":5.41,
"mdefUp":3.76,
"hpUp":70.83,
"isOpen":"true"
},
{
"id":"wa28",
"heroId":"hb11",
"atk":89,
"def":42,
"matk":131,
"mdef":35,
"hp":519,
"atkUp":6.13,
"defUp":2.75,
"matkUp":7.75,
"mdefUp":2.34,
"hpUp":50.38,
"isOpen":"true"
},
{
"id":"wa29",
"heroId":"hb12",
"atk":125,
"def":76,
"matk":113,
"mdef":64,
"hp":871,
"atkUp":6.27,
"defUp":4.91,
"matkUp":5.5,
"mdefUp":3.94,
"hpUp":64.69,
"isOpen":"true"
},
{
"id":"wa30",
"heroId":"hb13",
"atk":119,
"def":55,
"matk":124,
"mdef":72,
"hp":642,
"atkUp":5.27,
"defUp":3.14,
"matkUp":6.24,
"mdefUp":4.23,
"hpUp":70.76,
"isOpen":"true"
},
{
"id":"wa31",
"heroId":"hb14",
"atk":125,
"def":36,
"matk":79,
"mdef":31,
"hp":478,
"atkUp":7.42,
"defUp":2.38,
"matkUp":5.43,
"mdefUp":2.09,
"hpUp":46.4,
"isOpen":"true"
},
{
"id":"wa32",
"heroId":"hb15",
"atk":118,
"def":54,
"matk":119,
"mdef":78,
"hp":653,
"atkUp":5.21,
"defUp":3.11,
"matkUp":5.97,
"mdefUp":4.62,
"hpUp":72.02,
"isOpen":"true"
},
{
"id":"wa33",
"heroId":"hb16",
"atk":128,
"def":36,
"matk":73,
"mdef":30,
"hp":473,
"atkUp":7.54,
"defUp":2.38,
"matkUp":5.06,
"mdefUp":2.06,
"hpUp":46,
"isOpen":"true"
},
{
"id":"wa34",
"heroId":"hb17",
"atk":92,
"def":31,
"matk":187,
"mdef":36,
"hp":570,
"atkUp":4.59,
"defUp":2.07,
"matkUp":8.72,
"mdefUp":2.2,
"hpUp":55.96,
"isOpen":"true"
},
{
"id":"wa35",
"heroId":"hb18",
"atk":100,
"def":30,
"matk":189,
"mdef":36,
"hp":509,
"atkUp":5.03,
"defUp":2.05,
"matkUp":8.82,
"mdefUp":2.18,
"hpUp":50,
"isOpen":"true"
},
{
"id":"wa36",
"heroId":"hc01",
"atk":135,
"def":39,
"matk":83,
"mdef":33,
"hp":492,
"atkUp":7.99,
"defUp":2.52,
"matkUp":5.7,
"mdefUp":2.2,
"hpUp":47.79,
"isOpen":"true"
},
{
"id":"wa37",
"heroId":"hc02",
"atk":111,
"def":38,
"matk":195,
"mdef":41,
"hp":578,
"atkUp":5.52,
"defUp":2.53,
"matkUp":9.07,
"mdefUp":2.61,
"hpUp":56.77,
"isOpen":"true"
},
{
"id":"wa38",
"heroId":"hc03",
"atk":129,
"def":36,
"matk":74,
"mdef":30,
"hp":468,
"atkUp":7.59,
"defUp":2.36,
"matkUp":5.1,
"mdefUp":2.05,
"hpUp":45.52,
"isOpen":"true"
},
{
"id":"wa39",
"heroId":"hc04",
"atk":73,
"def":35,
"matk":131,
"mdef":29,
"hp":443,
"atkUp":4.98,
"defUp":2.28,
"matkUp":7.83,
"mdefUp":2.03,
"hpUp":43.15,
"isOpen":"true"
},
{
"id":"wa40",
"heroId":"hc05",
"atk":72,
"def":35,
"matk":131,
"mdef":29,
"hp":503,
"atkUp":4.9,
"defUp":2.27,
"matkUp":7.76,
"mdefUp":2.02,
"hpUp":48.91,
"isOpen":"true"
},
{
"id":"wa41",
"heroId":"hc06",
"atk":122,
"def":60,
"matk":130,
"mdef":76,
"hp":707,
"atkUp":5.36,
"defUp":3.39,
"matkUp":6.52,
"mdefUp":4.49,
"hpUp":77.87,
"isOpen":"true"
},
{
"id":"wa42",
"heroId":"hc07",
"atk":181,
"def":46,
"matk":103,
"mdef":39,
"hp":498,
"atkUp":10.17,
"defUp":2.72,
"matkUp":6.69,
"mdefUp":2.57,
"hpUp":51.58,
"isOpen":"true"
},
{
"id":"wa43",
"heroId":"hc08",
"atk":138,
"def":39,
"matk":75,
"mdef":33,
"hp":535,
"atkUp":8.16,
"defUp":2.54,
"matkUp":5.15,
"mdefUp":2.2,
"hpUp":52.03,
"isOpen":"true"
},
{
"id":"wa44",
"heroId":"hc09",
"atk":113,
"def":39,
"matk":192,
"mdef":42,
"hp":579,
"atkUp":5.66,
"defUp":2.54,
"matkUp":8.89,
"mdefUp":2.6,
"hpUp":56.87,
"isOpen":"true"
},
{
"id":"wa45",
"heroId":"hc10",
"atk":125,
"def":80,
"matk":110,
"mdef":58,
"hp":931,
"atkUp":6.28,
"defUp":5.15,
"matkUp":5.32,
"mdefUp":3.57,
"hpUp":69.14,
"isOpen":"true"
},
{
"id":"wa46",
"heroId":"hc11",
"atk":124,
"def":78,
"matk":115,
"mdef":66,
"hp":964,
"atkUp":6.19,
"defUp":5.07,
"matkUp":5.62,
"mdefUp":4.13,
"hpUp":71.51,
"isOpen":"true"
},
{
"id":"wa47",
"heroId":"hc12",
"atk":116,
"def":54,
"matk":118,
"mdef":78,
"hp":659,
"atkUp":5.13,
"defUp":3.08,
"matkUp":5.95,
"mdefUp":4.59,
"hpUp":72.71,
"isOpen":"true"
},
{
"id":"wa48",
"heroId":"hc13",
"atk":118,
"def":36,
"matk":185,
"mdef":39,
"hp":569,
"atkUp":5.91,
"defUp":2.45,
"matkUp":8.62,
"mdefUp":2.48,
"hpUp":55.8,
"isOpen":"true"
},
{
"id":"wa49",
"heroId":"hc14",
"atk":133,
"def":64,
"matk":128,
"mdef":77,
"hp":704,
"atkUp":6.72,
"defUp":3.65,
"matkUp":5.6,
"mdefUp":4.54,
"hpUp":77.7,
"isOpen":"true"
},
{
"id":"wa50",
"heroId":"hc15",
"atk":101,
"def":35,
"matk":188,
"mdef":42,
"hp":517,
"atkUp":5.08,
"defUp":2.28,
"matkUp":8.75,
"mdefUp":2.63,
"hpUp":50.77,
"isOpen":"true"
},
{
"id":"wa51",
"heroId":"hc16",
"atk":181,
"def":44,
"matk":89,
"mdef":33,
"hp":533,
"atkUp":10.17,
"defUp":2.62,
"matkUp":5.78,
"mdefUp":2.23,
"hpUp":55.26,
"isOpen":"true"
},
{
"id":"wa52",
"heroId":"hc17",
"atk":177,
"def":45,
"matk":92,
"mdef":35,
"hp":520,
"atkUp":9.96,
"defUp":2.68,
"matkUp":5.99,
"mdefUp":2.31,
"hpUp":53.9,
"isOpen":"true"
},
{
"id":"wa53",
"heroId":"hd01",
"atk":200,
"def":49,
"matk":89,
"mdef":36,
"hp":520,
"atkUp":11.3,
"defUp":2.9,
"matkUp":5.75,
"mdefUp":2.43,
"hpUp":53.89,
"isOpen":"true"
},
{
"id":"wa54",
"heroId":"hd02",
"atk":75,
"def":39,
"matk":137,
"mdef":34,
"hp":518,
"atkUp":5.13,
"defUp":2.55,
"matkUp":8.14,
"mdefUp":2.28,
"hpUp":50.45,
"isOpen":"true"
},
{
"id":"wa55",
"heroId":"hd03",
"atk":105,
"def":35,
"matk":178,
"mdef":38,
"hp":555,
"atkUp":5.18,
"defUp":2.36,
"matkUp":8.25,
"mdefUp":2.43,
"hpUp":54.5,
"isOpen":"true"
},
{
"id":"wa56",
"heroId":"hd04",
"atk":123,
"def":59,
"matk":118,
"mdef":75,
"hp":664,
"atkUp":6.17,
"defUp":3.3,
"matkUp":5.22,
"mdefUp":4.37,
"hpUp":73.15,
"isOpen":"true"
},
{
"id":"wa57",
"heroId":"hd05",
"atk":171,
"def":43,
"matk":91,
"mdef":34,
"hp":479,
"atkUp":9.66,
"defUp":2.61,
"matkUp":5.89,
"mdefUp":2.26,
"hpUp":49.69,
"isOpen":"true"
},
{
"id":"wa58",
"heroId":"hd06",
"atk":107,
"def":32,
"matk":175,
"mdef":36,
"hp":554,
"atkUp":5.35,
"defUp":2.13,
"matkUp":8.14,
"mdefUp":2.18,
"hpUp":54.46,
"isOpen":"true"
},
{
"id":"wa59",
"heroId":"hd07",
"atk":165,
"def":43,
"matk":81,
"mdef":32,
"hp":564,
"atkUp":9.33,
"defUp":2.51,
"matkUp":5.27,
"mdefUp":2.12,
"hpUp":58.38,
"isOpen":"true"
},
{
"id":"wa60",
"heroId":"hd08",
"atk":169,
"def":43,
"matk":81,
"mdef":32,
"hp":566,
"atkUp":9.56,
"defUp":2.5,
"matkUp":5.27,
"mdefUp":2.13,
"hpUp":58.67,
"isOpen":"true"
},
{
"id":"wa61",
"heroId":"hd09",
"atk":100,
"def":34,
"matk":189,
"mdef":38,
"hp":563,
"atkUp":5.04,
"defUp":2.26,
"matkUp":8.81,
"mdefUp":2.37,
"hpUp":55.31,
"isOpen":"true"
},
{
"id":"wa62",
"heroId":"hd10",
"atk":107,
"def":32,
"matk":178,
"mdef":36,
"hp":558,
"atkUp":5.32,
"defUp":2.11,
"matkUp":8.28,
"mdefUp":2.18,
"hpUp":54.78,
"isOpen":"true"
},
{
"id":"wa63",
"heroId":"hd11",
"atk":118,
"def":75,
"matk":107,
"mdef":60,
"hp":911,
"atkUp":5.93,
"defUp":4.84,
"matkUp":5.18,
"mdefUp":3.71,
"hpUp":67.62,
"isOpen":"true"
},
{
"id":"wa64",
"heroId":"hd12",
"atk":122,
"def":54,
"matk":120,
"mdef":79,
"hp":668,
"atkUp":6.16,
"defUp":3.1,
"matkUp":5.32,
"mdefUp":4.64,
"hpUp":73.59,
"isOpen":"true"
},
{
"id":"wa65",
"heroId":"hd13",
"atk":125,
"def":77,
"matk":108,
"mdef":61,
"hp":870,
"atkUp":6.28,
"defUp":4.95,
"matkUp":5.19,
"mdefUp":3.82,
"hpUp":64.54,
"isOpen":"true"
},
{
"id":"wa66",
"heroId":"hd14",
"atk":118,
"def":78,
"matk":104,
"mdef":57,
"hp":1004,
"atkUp":5.95,
"defUp":5.08,
"matkUp":5.08,
"mdefUp":3.5,
"hpUp":74.51,
"isOpen":"true"
},
{
"id":"wa67",
"heroId":"hd15",
"atk":171,
"def":45,
"matk":93,
"mdef":33,
"hp":531,
"atkUp":9.65,
"defUp":2.68,
"matkUp":6.07,
"mdefUp":2.22,
"hpUp":55.07,
"isOpen":"true"
},
{
"id":"wa68",
"heroId":"hd16",
"atk":129,
"def":35,
"matk":81,
"mdef":30,
"hp":528,
"atkUp":7.66,
"defUp":2.28,
"matkUp":5.56,
"mdefUp":2.08,
"hpUp":51.36,
"isOpen":"true"
},
{
"id":"wa69",
"heroId":"hd17",
"atk":77,
"def":36,
"matk":128,
"mdef":31,
"hp":490,
"atkUp":5.26,
"defUp":2.43,
"matkUp":7.62,
"mdefUp":2.12,
"hpUp":47.58,
"isOpen":"true"
},
{
"id":"wa70",
"heroId":"hd18",
"atk":130,
"def":59,
"matk":122,
"mdef":77,
"hp":690,
"atkUp":6.53,
"defUp":3.34,
"matkUp":5.43,
"mdefUp":4.5,
"hpUp":76.05,
"isOpen":"true"
},
{
"id":"wa71",
"heroId":"hd19",
"atk":100,
"def":33,
"matk":182,
"mdef":36,
"hp":598,
"atkUp":5.04,
"defUp":2.18,
"matkUp":8.46,
"mdefUp":2.26,
"hpUp":58.83,
"isOpen":"true"
},
{
"id":"wa72",
"heroId":"hb19",
"atk":136,
"def":36,
"matk":74,
"mdef":32,
"hp":524,
"atkUp":7.97,
"defUp":2.37,
"matkUp":5.02,
"mdefUp":2.11,
"hpUp":50.89,
"isOpen":"true"
},
{
"id":"wa73",
"heroId":"hd20",
"atk":104,
"def":33,
"matk":199,
"mdef":39,
"hp":522,
"atkUp":5.14,
"defUp":2.22,
"matkUp":9.23,
"mdefUp":2.4,
"hpUp":51.18,
"isOpen":"true"
}
]